qpt_generator/QPT.cpp
qpt_generator/QPT.h
qpt_generator/QPT.pxd
qpt_generator/__init__.py
qpt_generator/qpt_generator.cp37-win_amd64.pyd
qpt_generator/qpt_generator.cpp
qpt_generator/qpt_generator.pyx
qpt_generator-0.1.7.dist-info/LICENSE.txt
qpt_generator-0.1.7.dist-info/METADATA
qpt_generator-0.1.7.dist-info/WHEEL
qpt_generator-0.1.7.dist-info/top_level.txt
qpt_generator-0.1.7.dist-info/RECORD
