Metadata-Version: 2.1
Name: qpt-generator
Version: 0.1.7
Summary: Question Paper Template Generator
Home-page: https://github.com/Niraj-Kamdar/qpt_generator
Author: Niraj Kamdar
License: MIT
Download-URL: https://github.com/Niraj-Kamdar/qpt_generator/archive/master.zip
Keywords: question,paper,template,generator
Platform: UNKNOWN
Classifier: Development Status :: 4 - Beta
Classifier: Intended Audience :: Developers
Classifier: Topic :: Software Development :: Build Tools
Classifier: Natural Language :: English
Classifier: Operating System :: OS Independent
Classifier: License :: OSI Approved :: MIT License
Classifier: Programming Language :: Python :: 3
Classifier: Programming Language :: Python :: 3.5
Classifier: Programming Language :: Python :: 3.6
Classifier: Programming Language :: Python :: 3.7
Classifier: Programming Language :: Python :: 3.8
